{"name": "《古剑奇谭网络版》5月18日更新维护公告.html", "date": "2023-05-17", "totalLen": 550, "contentArr": [{"name": "秘境修复了玩家复活后不受首领战斗区域阻挡的问题。", "content": "【苍生冢】进行了一系列优化和调整：1、对技能【凝视】的目标选取进行了优化。2、降低了【宿体相】的攻击距离。3、修复了【道阻血凉】有时会停在原地的问题。4、【豪侠】难度下，【三仞三沮】不再清空【腥涎】的层数。5、降低了【凝聚的腐化】对【宿体相】的属性加成。", "leng": 127}, {"name": "界面更新", "content": "1）开启妙笔丹青时不再显示系统公告。2）团队面板的【自定义效果监控】和额外效果栏的【效果列表】的【本地账号同步】功能从【账号同步】中转移至新增的【效果账号同步】中。3）背包道具提取优化：1、新增快捷提取和一键提取功能。2、 修复“食材、水产、礼物类道具可以在有道具锁的状态下被提取”的问题。☆秘境修复了玩家复活后不受首领战斗区域阻挡的问题。【苍生冢】进行了一系列优化和调整：1、对技能【凝视】的目标选取进行了优化。2、降低了【宿体相】的攻击距离。3、修复了【道阻血凉】有时会停在原地的问题。4、【豪侠】难度下，【三仞三沮】不再清空【腥涎】的层数。5、降低了【凝聚的腐化】对【宿体相】的属性加成。《古剑奇谭网络版》项目组2023年5月17日", "leng": 319}, {"name": "活动更新", "content": "任务【春诵心弦】的奖励调整为心弦·千丝·限时*8。>>【心弦争歌】第四届心弦争歌【寄情音】复赛2阶段开启！仙家弟子可在心弦争歌投票界面为心仪的角色投票，或来到【步云洲·回忆】场景中对角色雕像使用心弦进行投票。", "leng": 104}], "authors": "《古剑奇谭网络版》项目组"}